raschii/__init__.py
raschii/air_phase_constant.py
raschii/air_phase_fenton.py
raschii/airy.py
raschii/base_classes.py
raschii/common.py
raschii/fenton.py
raschii/stokes.py
raschii/swd_tools.py
raschii/cmd/__init__.py
raschii/cmd/plot.py
raschii/cmd/swd.py
raschii-1.1.0.dist-info/METADATA
raschii-1.1.0.dist-info/WHEEL
raschii-1.1.0.dist-info/licenses/LICENSE
raschii-1.1.0.dist-info/RECORD
