Metadata-Version: 2.4
Name: raschii
Version: 1.1.0
Summary: A Python implementation of nonlinear regular wave theories (Stokes 2nd to 5th order and Fenton stream function waves).
Project-URL: Homepage, https://github.com/TormodLandet/raschii
Project-URL: Source, https://github.com/TormodLandet/raschii
Project-URL: Documentation, https://raschii.readthedocs.io/
Author-email: Tormod Landet <tormod@landet.net>
License-Expression: Apache-2.0
License-File: LICENSE
Keywords: Airy,Fenton,Stokes,function,ocean,stream,waves
Classifier: Development Status :: 5 - Production/Stable
Classifier: Intended Audience :: Science/Research
Classifier: License :: OSI Approved :: Apache Software License
Classifier: Programming Language :: Python :: 3
Classifier: Topic :: Scientific/Engineering :: Mathematics
Classifier: Topic :: Scientific/Engineering :: Physics
Requires-Python: >=3.10
Requires-Dist: numpy
